aliyunsdkbuss/__init__.py
aliyunsdkbuss/request/__init__.py
aliyunsdkbuss/request/v20220822/BusinessResultServiceRequest.py
aliyunsdkbuss/request/v20220822/CreateUserInvestigationInfoQueryTaskRequest.py
aliyunsdkbuss/request/v20220822/FindInstanceInfoRequest.py
aliyunsdkbuss/request/v20220822/FindUserAvailbleResourcesRequest.py
aliyunsdkbuss/request/v20220822/GetSecurityEventDetailRequest.py
aliyunsdkbuss/request/v20220822/PunishResourceSearchRequest.py
aliyunsdkbuss/request/v20220822/RiskEventSyncRequest.py
aliyunsdkbuss/request/v20220822/SearchPunishEventsRequest.py
aliyunsdkbuss/request/v20220822/SearchPunishRecordsRequest.py
aliyunsdkbuss/request/v20220822/SearchPunishRequestRequest.py
aliyunsdkbuss/request/v20220822/UpdateSecurityEventStatusRequest.py
aliyunsdkbuss/request/v20220822/__init__.py
aliyun_python_sdk_buss-1.0.0.dist-info/LICENSE
aliyun_python_sdk_buss-1.0.0.dist-info/METADATA
aliyun_python_sdk_buss-1.0.0.dist-info/WHEEL
aliyun_python_sdk_buss-1.0.0.dist-info/top_level.txt
aliyun_python_sdk_buss-1.0.0.dist-info/RECORD
